mapclassif_Iron/__init__.py
mapclassif_Iron/classifiers.py
mapclassif_Iron/test_fisher_jenks_means.py
mapclassif_Iron/datasets/__init__.py
mapclassif_Iron/datasets/calemp/README.md
mapclassif_Iron/datasets/calemp/__init__.py
mapclassif_Iron/datasets/calemp/calempdensity.csv
mapclassif_Iron/datasets/calemp/data.py
mapclassif_Iron-2.6.3.dist-info/LICENSE.txt
mapclassif_Iron-2.6.3.dist-info/METADATA
mapclassif_Iron-2.6.3.dist-info/WHEEL
mapclassif_Iron-2.6.3.dist-info/top_level.txt
mapclassif_Iron-2.6.3.dist-info/RECORD
