Metadata-Version: 2.1
Name: mapclassif-Iron
Version: 2.6.3
Summary: Classification Schemes for Choropleth Maps.
Maintainer-email: James Parrott <james.parrott@proton.me>
License: BSD 3-Clause
Project-URL: Repository, https://github.com/JamesParrott/mapclassif-Iron
Keywords: spatial statistics,geovisualizaiton
Classifier: Programming Language :: Python :: 2
Classifier: Programming Language :: Python :: 3
Classifier: Programming Language :: Python :: 3.9
Classifier: Programming Language :: Python :: 3.10
Classifier: Programming Language :: Python :: 3.11
Classifier: License :: OSI Approved :: BSD License
Classifier: Operating System :: OS Independent
Classifier: Intended Audience :: Science/Research
Classifier: Topic :: Scientific/Engineering :: GIS
Requires-Python: >=2.7
License-File: LICENSE.txt
Provides-Extra: tests
Requires-Dist: numpy ; extra == 'tests'
Requires-Dist: pytest ; extra == 'tests'
